setup.py
AiPangu/__init__.py
AiPangu/check_params.cp36-win_amd64.pyd
AiPangu/pangu.cp36-win_amd64.pyd
AiPangu/tools.cp36-win_amd64.pyd
AiPangu/check_params.pyi
AiPangu/pangu.pyi
ai_pangu.egg-info/PKG-INFO
ai_pangu.egg-info/SOURCES.txt
ai_pangu.egg-info/dependency_links.txt
ai_pangu.egg-info/requires.txt
ai_pangu.egg-info/top_level.txt